fortnite_python/__init__.py
fortnite_python/base.py
fortnite_python/domain.py
fortnite_python/exceptions.py
fortnite_python-0.3.3.dist-info/LICENSE
fortnite_python-0.3.3.dist-info/METADATA
fortnite_python-0.3.3.dist-info/WHEEL
fortnite_python-0.3.3.dist-info/top_level.txt
fortnite_python-0.3.3.dist-info/RECORD
