Metadata-Version: 2.1
Name: fortnite-python
Version: 0.3.3
Summary: Python wrapper for http://fortnitetracker.com/ api.
Home-page: https://github.com/xcodinas/fortnite-python
Author: Xavier Codinas
Author-email: xavier19966@gmail.com
License: MIT
Platform: UNKNOWN
Classifier: Development Status :: 3 - Alpha
Classifier: License :: OSI Approved :: MIT License
Classifier: Natural Language :: English
Classifier: Operating System :: OS Independent
Classifier: Programming Language :: Python :: 3
Classifier: Programming Language :: Python :: 3.6
Classifier: Topic :: Utilities
Requires-Dist: requests (>=2.18.4)
Requires-Dist: furl (>=1.0.1)
Requires-Dist: enum34 (>=1.1.6); python_version<='3.4'
